.project
.pydevproject
LICENSE
MANIFEST.in
PKG-INFO
README.txt
messages-js.cfg
setup.cfg
setup.py
Piwik4Trac.egg-info/PKG-INFO
Piwik4Trac.egg-info/SOURCES.txt
Piwik4Trac.egg-info/dependency_links.txt
Piwik4Trac.egg-info/entry_points.txt
Piwik4Trac.egg-info/namespace_packages.txt
Piwik4Trac.egg-info/requires.txt
Piwik4Trac.egg-info/top_level.txt
tracext/__init__.py
tracext.piwik.egg-info/SOURCES.txt
tracext.piwik.egg-info/dependency_links.txt
tracext.piwik.egg-info/entry_points.txt
tracext.piwik.egg-info/namespace_packages.txt
tracext.piwik.egg-info/requires.txt
tracext.piwik.egg-info/top_level.txt
tracext/piwik/__init__.py
tracext/piwik/admin.py
tracext/piwik/web_ui.py
tracext/piwik/htdocs/piwik.css
tracext/piwik/locale/messages.pot
tracext/piwik/locale/fr/LC_MESSAGES/piwik4trac.po
tracext/piwik/templates/piwik_admin.html
tracext/piwik/templates/piwik_analytics.html