Metadata-Version: 1.0
Name: Piwik4Trac
Version: 0.1.0
Summary: Trac plugin to enable your trac environment to be logged by a Piwik server
Home-page: http://technique.arscenic.org/services-web/subversion-et-trac/ameliorer-et-optimiser-trac/article/trac-et-piwik-analyse-des
Author: kent1
Author-email: kent1@arscenic.info
License: GNU/GPL v3
Download-URL: http://python.org/pypi/tracext.piwik
Keywords: trac plugin piwik
Platform: UNKNOWN
Classifier: Framework :: Trac
